{
    "$schema": "vscode://schemas/color-theme",
    "semanticHighlighting": true,
    "tokenColors": [
        {
            "name": "Comment",
            "scope": [
                "comment",
                "meta.separator",
                "markup.quote",
                "unused.comment",
                "wildcard.comment"
            ],
            "settings": {
                "fontStyle": "italic",
                "foreground": "#5C6370"
            }
        },
        {
            "name": "Doc Comment",
            "scope": [
                "comment.block.documentation.js storage.type.class.doc",
                "comment.block.documentation.js storage.type.class.jsdoc"
            ],
            "settings": {
                "fontStyle": "bold italic",
                "foreground": "#ABB2BF88"
            }
        },
        {
            "name": "this",
            "scope": [
                "variable.language.arguments",
                "variable.language.constructor",
                "variable.language.prototype",
                "variable.language.rust",
                "variable.language.this",
                "variable.language.super"
            ],
            "settings": {
                "fontStyle": "italic",
                "foreground": "#be5046"
            }
        },
        {
            "name": "Blue",
            "scope": [
                "entity.name.accessor.js",
                "entity.name.function",
                "entity.name.function.method.js",
                "entity.other.attribute-name.id",
                "keyword.other.special-method",
                "meta.function-call.object.php",
                "meta.function-call.php",
                "meta.function-call.static.php",
                "meta.method-call.java meta.method.java",
                "meta.require.ruby",
                "string.other.link.title.markdown",
                "support.function.funchand.php",
                "support.function.console.js",
                "support.function.dom",
                "support.function.go",
                "support.function.json.ts",
                "support.function.math",
                "support.function.misc.scss",
                "support.function.misc.css"
            ],
            "settings": {
                "foreground": "#61afef"
            }
        },
        {
            "name": "Green",
            "scope": [
                "constant.character.literal.scala",
                "entity.other.inherited-class.php",
                "markup.fenced_code.block.markdown",
                "markup.inline.raw.markdown",
                "punctuation.definition.string",
                "source.sql.embedded.php",
                "string.quasi.js",
                "string.quoted.double",
                "string.quoted.single",
                "string.unquoted"
            ],
            "settings": {
                "foreground": "#98c379"
            }
        },
        {
            "name": "Node",
            "scope" : [
                "support.module.node.js",
                "support.type.object.node.js",
                "support.type.object.process.js",
                "variable.language.ruby"
            ],
            "settings": {
                "foreground": "#36A252"
            }
        },
        {
            "name": "Orange Dark",
            "scope": [
                "constant.language",
                "constant.language.php",
                "entity.name.goto-label.php",
                "constant.numeric",
                "constant.other.class.php",
                "constant.other.php",
                "entity.other.attribute-name",
                "entity.other.attribute-name.attribute.scss",
                "entity.other.attribute-name.localname.xml",
                "entity.other.attribute-name.pseudo-class.css",
                "entity.other.attribute-name.pseudo-element.css",
                "keyword.other.unit.scss",
                "meta.at-rule.include.scss",
                "meta.attribute.rust",
                "meta.set.variable.scss",
                "punctuation.definition.constant",
                "support.constant.ext.php",
                "support.constant.font-name",
                "support.constant.json",
                "support.constant.math",
                "support.constant.media.css",
                "support.constant.property-value",
                "support.constant.std.php",
                "support.type.object.console.js",
                "variable.other.constant",
                "variable.other.property"
            ],
            "settings": {
                "foreground": "#d19a66"
            }
        },
        {
            "name": "Orange Light",
            "scope": [
                "constant.other.database-name.sql",
                "constant.numeric.sql",
                "constant.other.table-name.sql",
                "entity.name.class",
                "entity.name.import.scala",
                "entity.name.package",
                "entity.name.type",
                "entity.name.type.class",
                "entity.name.type.module",
                "entity.name.type.namespace.cs",
                "entity.name.type.new.js",
                "entity.other.attribute-name.class.css",
                "entity.other.inherited-class",
                "meta.tag.sgml.doctype.html",
                "storage.modifier.import.java",
                "storage.modifier.package.java",
                "storage.type.cs",
                "storage.type.java",
                "storage.type.php",
                "storage.type.primitive",
                "support.class",
                "support.constant.core",
                "support.other.namespace.php",
                "support.other.namespace.use.php",
                "support.variable.dom",
                "support.variable.property",
                "tag.decorator entity.name.tag",
                "variable.import.scala",
                "variable.other.alias.yaml",
                "variable.other.class.js"
            ],
            "settings": {
                "foreground": "#e5c07b"
            }
        },
        {
            "name": "Purple",
            "scope": [
                "keyword.control",
                "keyword.control.anchor.regexp",
                "keyword.control.at-rule.font-face.css",
                "keyword.control.at-rule.function.scss",
                "keyword.control.at-rule.import.scss",
                "keyword.control.at-rule.include.scss",
                "keyword.control.at-rule.media.css",
                "keyword.control.at-rule.media.scss",
                "keyword.control.at-rule.mixin.scss",
                "keyword.control.class.ruby",
                "keyword.control.conditional",
                "keyword.control.def.ruby",
                "keyword.control.export.ts",
                "keyword.control.flow",
                "keyword.control.for.scss",
                "keyword.control.import.include.php",
                "keyword.control.loop",
                "keyword.control.module",
                "keyword.control.pseudo-method.ruby",
                "keyword.control.return.scss",
                "keyword.control.ruby",
                "keyword.control.shell",
                "keyword.control.start-block.ruby",
                "keyword.declaration",
                "keyword.function.go",
                "keyword.import.go",
                "keyword.operator.error-control.php",
                "keyword.operator.js",
                "keyword.operator.or.regexp",
                "keyword.other.alias.sql",
                "keyword.other.class.cs",
                "keyword.other.data-integrity.sql",
                "keyword.other.DDL.create.II.sql",
                "keyword.other.DML.sql",
                "keyword.other.fn.rust",
                "keyword.other.function.use.php",
                "keyword.other.import",
                "keyword.other.import.static",
                "keyword.other.namespace.cs",
                "keyword.other.namespace.php",
                "keyword.other.new",
                "keyword.other.new.php",
                "keyword.other.order.sql",
                "keyword.other.package.java",
                "keyword.other.phpdoc.php",
                "keyword.other.rust",
                "keyword.other.scoping.scala",
                "keyword.other.use.php",
                "keyword.other.using.cs",
                "keyword.other.where.rust",
                "keyword.package.go",
                "keyword.struct.go",
                "keyword.type",
                "punctuation.definition.entity.begin.bracket.square.css",
                "punctuation.definition.entity.end.bracket.square.css",
                "punctuation.definition.group.regexp",
                "punctuation.section.function.css",
                "punctuation.section.scope.elixir",
                "storage.modifier",
                "storage.class.std.rust",
                "storage.type",
                "storage.type.class",
                "storage.type.extends.js",
                "storage.type.function.js",
                "storage.type.namespace.ts"
            ],
            "settings": {
                "foreground": "#c678dd"
            }
        },
        {
            "name": "Red Dark",
            "scope": [
                "punctuation.section.embedded.begin",
                "punctuation.section.embedded.end",
                "variable.interpolation.scss"
            ],
            "settings": {
                "foreground": "#B9362B"
            }
        },
        {
            "name": "Red Light",
            "scope": [
                "beginning.punctuation.definition.list.markdown",
                "constant.other.object.key.js",
                "constant.other.object.key.js string.unquoted",
                "constant.other.reference.link.markdown",
                "entity.name.section.markdown",
                "entity.name.tag",
                "entity.name.val.declaration",
                "entity.name.variable.field.cs",
                "entity.name.variable.local.cs",
                "entity.name.variable.parameter.cs",
                "markup.heading.setext",
                "meta.class.java meta.class.body.java meta.method.java meta.method.body.java",
                "meta.definition.variable.name.java",
                "meta.object-literal.key",
                "meta.set.variable punctuation.separator.key-value.scss",
                "meta.type_params.rust",
                "punctuation.definition.heading.markdown",
                "punctuation.definition.variable.shell",
                "source.js meta.instance.constructor",
                "string.quoted.double.sql.php",
                "string.quoted.single.sql.php",
                "support.type.object.dom.js",
                "support.type.property-name.json",
                "variable.css",
                "variable.scss",
                "variable.argument.css",
                "variable.object.property.ts",
                "variable.other.assignment.go",
                "variable.other.block.ruby",
                "variable.other.bracket.shell",
                "variable.other.class.php",
                "variable.other.declaration.scala",
                "variable.other.dollar",
                "variable.other.global.php",
                "variable.other.global.safer.php",
                "variable.other.loop.shell",
                "variable.other.normal.shell",
                "variable.other.object",
                "variable.other.php",
                "variable.other.positional.shell",
                "variable.other.property.static.js",
                "variable.other.readwrite",
                "variable.other.special.shell",
                "variable.package.scala",
                "variable.parameter"
            ],
            "settings": {
                "foreground": "#e06c75"
            }
        },
        {
            "name": "Cyan",
            "scope": [
                "constant.character.escape",
                "constant.other.symbol",
                "constant.other.symbol.hashkey punctuation.definition.constant",
                "keyword.control.new.java",
                "keyword.operator.address.go",
                "keyword.operator.arithmetic",
                "keyword.operator.assignment",
                "keyword.operator.assignment.augmented",
                "keyword.operator.bitwise.php",
                "keyword.operator.comparison",
                "keyword.operator.decrement.go",
                "keyword.operator.increment.go",
                "keyword.operator.increment-decrement",
                "keyword.operator.logical",
                "keyword.operator.logical.and.media.css",
                "keyword.operator.logical.php",
                "keyword.operator.misc.rust",
                "keyword.operator.new",
                "keyword.operator.other.elixir",
                "keyword.operator.relational",
                "keyword.operator.scala",
                "keyword.operator.sigil.rust",
                "keyword.operator.ternary.js",
                "meta.tag.sgml.html punctuation.definition.tag.html",
                "punctuation.definition.tag.js",
                "storage.type.accessor.js",
                "storage.type.annotation.java",
                "string.regexp.js",
                "string.regexp.single-quoted.php",
                "string.regexp.double-quoted.php",
                "support.function.array.php",
                "support.function.basic_functions.php",
                "support.function.bcmath.php",
                "support.function.builtin",
                "support.function.classobj.php",
                "support.function.construct.output.php",
                "support.function.construct.php",
                "support.function.core.rust",
                "support.function.curl.php",
                "support.function.datetime.php",
                "support.function.dir.php",
                "support.function.errorfunc.php",
                "support.function.file.php",
                "support.function.gmp.php",
                "support.function.hash.php",
                "support.function.iconv.php",
                "support.function.image.php",
                "support.function.info.php",
                "support.function.intl.php",
                "support.function.js",
                "support.function.json.php",
                "support.function.ldap.php",
                "support.function.magic.php",
                "support.function.math.php",
                "support.function.mhash.php",
                "support.function.mutator.js",
                "support.function.mysql.php",
                "support.function.openssl.php",
                "support.function.output.php",
                "support.function.password.php",
                "support.function.pgsql.php",
                "support.function.php_apache.php",
                "support.function.php_imap.php",
                "support.function.php_mssql.php",
                "support.function.php_pcre.php",
                "support.function.php_spl.php",
                "support.function.mail.php",
                "support.function.network.php",
                "support.function.session.php",
                "support.function.std.rust",
                "support.function.streamsfuncs.php",
                "support.function.string.php",
                "support.function.ts",
                "support.function.url.css",
                "support.function.url.php",
                "support.function.var.php",
                "support.type.class.flowtype",
                "support.type.object.module.js keyword.operator.accessor.js",
                "support.type.object.module.js keyword.operator.accessor.js support.type.object.module.js",
                "support.type.primitive",
                "support.type.vendored.property-name.css",
                "source.css.scss keyword.control.operator"
            ],
            "settings": {
                "foreground": "#56b6c2"
            }
        },
        {
            "name": "Gray",
            "scope": [
                "meta.class.body.java",
                "meta.definition.variable.java",
                "meta.method.body.java",
                "meta.method.identifier.java",
                "punctuation.definition.method-parameters.begin.java",
                "punctuation.definition.method-parameters.end.java",
                "punctuation.definition.parameters.begin.bracket.round.scss",
                "punctuation.definition.parameters.end.bracket.round.scss",
                "punctuation.separator.key-value.js",
                "punctuation.terminator.java"
            ],
            "settings": {
                "foreground": "#ABB2BF"
            }
        },
        {
            "name": "Invalid Illegal",
            "scope": [
                "invalid.illegal",
                "invalid.illegal.scss"
            ],
            "settings": {
                "foreground": "#E05252"
            }
        },
        {
            "name": "Italic",
            "scope": "markup.italic",
            "settings": {
                "foreground": "#c678dd",
                "fontStyle": "italic"
            }
        },
        {
            "name": "Bold",
            "scope": "markup.bold",
            "settings" : {
                "foreground": "#d19a66",
                "fontStyle": "bold"
            }
        },
        {
            "name": "None",
            "scope"			: "",
            "settings": {
                "foreground": "#ABB2BF"
            }
        }
    ],
    "colors": {
        "activityBar.activeBackground"                          : "",
        "activityBar.activeBorder"                              : "",
        "activityBar.activeFocusBorder"                         : "",
        "activityBar.dropBorder"                                : "",
        "activityBar.inactiveForeground"                        : "",
        "breadcrumb.background"                                 : "",
        "breadcrumbPicker.background"                               : "#2C323C",
        "button.border"                                         : "",
        "button.secondaryBackground"                            : "",
        "button.secondaryForeground"                            : "",
        "button.secondaryHoverBackground"                       : "",
        "charts.blue"                                           : "",
        "charts.foreground"                                     : "",
        "charts.green"                                          : "",
        "charts.lines"                                          : "",
        "charts.orange"                                         : "",
        "charts.purple"                                         : "",
        "charts.red"                                            : "",
        "charts.yellow"                                         : "",
        "checkbox.background"                                   : "",
        "checkbox.border"                                       : "",
        "checkbox.foreground"                                   : "",
        "contrastActiveBorder"                                  : "",
        "contrastBorder"                                        : "",
        "debugConsole.errorForeground"                          : "",
        "debugConsole.infoForeground"                           : "",
        "debugConsole.sourceForeground"                         : "",
        "debugConsole.warningForeground"                        : "",
        "debugConsoleInputIcon.foreground"                      : "",
        "debugExceptionWidget.background"                           : "#23272E",
        "debugIcon.breakpointCurrentStackframeForeground"       : "",
        "debugIcon.breakpointDisabledForeground"                : "",
        "debugIcon.breakpointForeground"                        : "",
        "debugIcon.breakpointStackframeForeground"              : "",
        "debugIcon.breakpointUnverifiedForeground"              : "",
        "debugIcon.continueForeground"			                : "",
        "debugIcon.disconnectForeground"		                : "",
        "debugIcon.pauseForeground"			                    : "",
        "debugIcon.restartForeground"			                : "",
        "debugIcon.startForeground"			                    : "",
        "debugIcon.stepBackForeground"			                : "",
        "debugIcon.stepIntoForeground"			                : "",
        "debugIcon.stepOutForeground"			                : "",
        "debugIcon.stepOverForeground"			                : "",
        "debugIcon.stopForeground"			                    : "",
        "debugTokenExpression.boolean"			                : "",
        "debugTokenExpression.error"			                : "",
        "debugTokenExpression.name"			                    : "",
        "debugTokenExpression.number"			                : "",
        "debugTokenExpression.string"			                : "",
        "debugTokenExpression.value"			                : "",
        "debugToolBar.border"			                        : "",
        "debugView.exceptionLabelBackground"			        : "",
        "debugView.exceptionLabelForeground"			        : "",
        "debugView.stateLabelBackground"			            : "",
        "debugView.stateLabelForeground"			            : "",
        "debugView.valueChangedHighlight"			            : "",
        "descriptionForeground"			                        : "",
        "diffEditor.border"			                            : "",
        "diffEditor.diagonalFill"			                    : "",
        "diffEditor.insertedTextBackground"                         : "#39CA7430",
        "diffEditor.insertedTextBorder"                         : "",
        "diffEditor.removedTextBackground"                          : "#B7373060",
        "diffEditor.removedTextBorder"                          : "",
        "dropdown.background"                                       : "#353942",
        "dropdown.border"                                           : "#353942",
        "dropdown.foreground"                                       : "#93A1A1",
        "dropdown.listBackground"			                    : "",
        "editor.background"                                         : "#282C34",
        "editor.findMatchBackground"                                : "#558EFC",
        "editor.findMatchBorder"			                    : "",
        "editor.findMatchHighlightBackground"                       : "#324464",
        "editor.findMatchHighlightBorder"			            : "",
        "editor.findRangeHighlightBackground"                       : "#324464",
        "editor.findRangeHighlightBorder"			            : "",
        "editor.focusedStackFrameHighlightBackground"			: "",
        "editor.foldBackground"			                        : "",
        "editor.foreground"                                         : "#ABB2BF",
        "editor.hoverHighlightBackground"                           : "#3E4451",
        "editor.lineHighlightBackground"                            : "#2C323C",
        "editor.lineHighlightBorder"                                : "#2C323C",
        "editor.linkedEditingBackground"			            : "",
        "editor.rangeHighlightBackground"                           : "#3E4451",
        "editor.rangeHighlightBorder"			                : "",
        "editor.selectionBackground"                                : "#3E4451",
        "editor.selectionForeground"			                : "",
        "editor.selectionHighlightBackground"                       : "#3E4451",
        "editor.selectionHighlightBorder"			            : "",
        "editor.snippetFinalTabstopHighlightBackground"			: "",
        "editor.snippetFinalTabstopHighlightBorder"			    : "",
        "editor.snippetTabstopHighlightBackground"			    : "",
        "editor.snippetTabstopHighlightBorder"			        : "",
        "editor.stackFrameHighlightBackground"			        : "",
        "editor.symbolHighlightBackground"			            : "",
        "editor.symbolHighlightBorder"			                : "",
        "editor.wordHighlightBorder"			                : "",
        "editor.wordHighlightStrongBorder"			            : "",
        "editorBracketMatch.background"                             : "#558EFF",
        "editorBracketMatch.border"                                 : "#558EFF",
        "editorCodeLens.foreground"                                 : "#ffffff44",
        "editorCursor.background"			                    : "",
        "editorError.background"			                    : "",
        "editorError.border"                                        : "#7049B800",
        "editorError.foreground"                                    : "#DD4941",
        "editorGroup.border"                                        : "#30343C",
        "editorGroup.emptyBackground"			                : "",
        "editorGroup.focusedEmptyBorder"			            : "",
        "editorGroupHeader.border"		    	                : "",
        "editorGroupHeader.noTabsBackground"                        : "#1E1F29",
        "editorGroupHeader.tabsBackground"                          : "#1C1D25",
        "editorGroupHeader.tabsBorder"                              : "#00000066",
        "editorGutter.addedBackground"                              : "#39CA74",
        "editorGutter.background"                                   : "#282C34",
        "editorGutter.commentRangeForeground"			        : "",
        "editorGutter.deletedBackground"                            : "#DD4941",
        "editorGutter.foldingControlForeground"			        : "",
        "editorGutter.modifiedBackground"                           : "#EAC72E",
        "editorHint.border"			                            : "",
        "editorHint.foreground"			                        : "",
        "editorHoverWidget.background"                              : "#1E1F29",
        "editorHoverWidget.foreground"			                : "",
        "editorHoverWidget.statusBarBackground"			        : "",
        "editorIndentGuide.activeBackground"			        : "",
        "editorIndentGuide.background"                              : "#4B5262",
        "editorInfo.background"			                        : "",
        "editorInfo.border"			                            : "",
        "editorInfo.foreground"			                        : "",
        "editorLightBulb.foreground"			                : "",
        "editorLightBulbAutoFix.foreground"			            : "",
        "editorLineNumber.activeForeground"			            : "",
        "editorLineNumber.foreground"                               : "#4B5263",
        "editorLink.activeForeground"                               : "#5AB6C1",
        "editorMarkerNavigation.background"                     : "",
        "editorMarkerNavigationError.background"                : "",
        "editorMarkerNavigationInfo.background"			        : "",
        "editorMarkerNavigationWarning.background"			    : "",
        "editorOverviewRuler.addedForeground"			        : "",
        "editorOverviewRuler.background"			            : "",
        "editorOverviewRuler.border"                                : "#00000020",
        "editorOverviewRuler.bracketMatchForeground"			: "",
        "editorOverviewRuler.commonContentForeground"           : "",
        "editorOverviewRuler.currentContentForeground"          : "",
        "editorOverviewRuler.deletedForeground"			        : "",
        "editorOverviewRuler.errorForeground"			        : "",
        "editorOverviewRuler.findMatchForeground"			    : "",
        "editorOverviewRuler.incomingContentForeground"         : "",
        "editorOverviewRuler.infoForeground"			        : "",
        "editorOverviewRuler.modifiedForeground"			    : "",
        "editorOverviewRuler.rangeHighlightForeground"			: "",
        "editorOverviewRuler.selectionHighlightForeground"		: "",
        "editorOverviewRuler.warningForeground"		        	: "",
        "editorOverviewRuler.wordHighlightForeground"			: "",
        "editorOverviewRuler.wordHighlightStrongForeground"		: "",
        "editorPane.background"			                        : "",
        "editorRuler.foreground"                                    : "#3C4049",
        "editorSuggestWidget.background"			            : "",
        "editorSuggestWidget.border"                                : "#353A42",
        "editorUnnecessaryCode.border"			                : "",
        "editorUnnecessaryCode.opacity"			                : "",
        "editorWarning.background"			                    : "",
        "editorWarning.border"                                      : "#7049B800",
        "editorWarning.foreground"                                  : "#EAC72E",
        "editorWhitespace.foreground"                               : "#3B4048",
        "editorWidget.background"                                   : "#282C34",
        "editorWidget.border"			                        : "",
        "editorWidget.foreground"			                    : "",
        "editorWidget.resizeBorder"			                    : "",
        "errorForeground"                                       : "",
        "extensionBadge.remoteBackground"			            : "",
        "extensionBadge.remoteForeground"			            : "",
        "extensionIcon.starForeground"			                : "",
        "foreground"                                                : "#9096A2",
        "gitDecoration.addedResourceForeground"			        : "",
        "gitDecoration.conflictingResourceForeground"			: "",
        "gitDecoration.deletedResourceForeground"			    : "",
        "gitDecoration.ignoredResourceForeground"			    : "",
        "gitDecoration.modifiedResourceForeground"			    : "",
        "gitDecoration.renamedResourceForeground"			    : "",
        "gitDecoration.stageDeletedResourceForeground"		    : "",
        "gitDecoration.stageModifiedResourceForeground"		    : "",
        "gitDecoration.submoduleResourceForeground"			    : "",
        "gitDecoration.untrackedResourceForeground"			    : "",
        "icon.foreground"			                            : "",
        "input.background"                                          : "#35394200",
        "input.foreground"                                          : "#ABB2BF",
        "input.placeholderForeground"                               : "#4F525D",
        "inputOption.activeBackground"			                : "",
        "inputOption.activeForeground"			                : "",
        "inputValidation.errorBackground"                           : "#6D1C18",
        "inputValidation.errorBorder"                               : "#F1453D",
        "inputValidation.errorForeground"			            : "",
        "inputValidation.infoBackground"                        : "",
        "inputValidation.infoBorder"                            : "",
        "inputValidation.infoForeground"			            : "",
        "inputValidation.warningBackground"                         : "#43392E",
        "inputValidation.warningBorder"                             : "#EAC72E",
        "inputValidation.warningForeground"		                : "",
        "keybindingLabel.background"			                : "",
        "keybindingLabel.border"			                    : "",
        "keybindingLabel.bottomBorder"			                : "",
        "keybindingLabel.foreground"			                : "",
        "list.deemphasizedForeground"			                : "",
        "list.errorForeground"			                        : "",
        "list.filterMatchBackground"			                : "",
        "list.filterMatchBorder"			                    : "",
        "list.focusForeground"                                      : "#ffffff",
        "list.focusOutline"			                            : "",
        "list.highlightForeground"                                  : "#ffffff",
        "list.hoverBackground"                                      : "#23272E",
        "list.hoverForeground"                                      : "#ABB2BF",
        "list.inactiveFocusBackground"			                : "",
        "list.inactiveFocusOutline"			                    : "",
        "list.inactiveSelectionBackground"                          : "#292E34",
        "list.inactiveSelectionForeground"                          : "#ABB2BF",
        "list.invalidItemForeground"		                    : "",
        "list.warningForeground"			                    : "",
        "listFilterWidget.background"		                    : "",
        "listFilterWidget.noMatchesOutline"	                    : "",
        "listFilterWidget.outline"			                    : "",
        "menu.background"			                            : "",
        "menu.border"			                                : "",
        "menu.foreground"			                            : "",
        "menu.selectionBackground"			                    : "",
        "menu.selectionBorder"			                        : "",
        "menu.selectionForeground"			                    : "",
        "menu.separatorBackground"			                    : "",
        "menubar.selectionBackground"		                    : "",
        "menubar.selectionBorder"			                    : "",
        "menubar.selectionForeground"	                        : "",
        "merge.border"                                              : "#1E1F29",
        "merge.commonContentBackground"                             : "",
        "merge.commonHeaderBackground"                              : "",
        "merge.currentContentBackground"                            : "#B737307F",
        "merge.currentHeaderBackground"                             : "#B73730",
        "merge.incomingContentBackground"                           : "#2E73667F",
        "merge.incomingHeaderBackground"                            : "#2E7366",
        "minimap.background"			                        : "",
        "minimap.errorHighlight"			                    : "",
        "minimap.findMatchHighlight"			                : "",
        "minimap.selectionHighlight"			                : "",
        "minimap.warningHighlight"			                    : "",
        "minimapGutter.addedBackground"			                : "",
        "minimapGutter.deletedBackground"			            : "",
        "minimapGutter.modifiedBackground"			            : "",
        "minimapSlider.activeBackground"			            : "",
        "minimapSlider.background"			                    : "",
        "minimapSlider.hoverBackground"			                : "",
        "notebook.cellBorderColor"			                    : "",
        "notebook.cellHoverBackground"			                : "",
        "notebook.cellInsertionIndicator"			            : "",
        "notebook.cellStatusBarItemHoverBackground"	            : "",
        "notebook.cellToolbarSeparator"			                : "",
        "notebook.focusedCellBackground"			            : "",
        "notebook.focusedCellBorder"			                : "",
        "notebook.focusedEditorBorder"			                : "",
        "notebook.focusedRowBorder"			                    : "",
        "notebook.inactiveFocusedCellBorder"		            : "",
        "notebook.inactiveSelectedCellBorder"		            : "",
        "notebook.outputContainerBackgroundColor"	            : "",
        "notebook.rowHoverBackground"			                : "",
        "notebook.selectedCellBackground"			            : "",
        "notebook.selectedCellBorder"			                : "",
        "notebook.symbolHighlightBackground"			        : "",
        "notebookScrollbarSlider.activeBackground"		        : "",
        "notebookScrollbarSlider.background"			        : "",
        "notebookScrollbarSlider.hoverBackground"			    : "",
        "notebookStatusErrorIcon.foreground"			        : "",
        "notebookStatusRunningIcon.foreground"			        : "",
        "notebookStatusSuccessIcon.foreground"			        : "",
        "notificationCenter.border"			                    : "",
        "notificationCenterHeader.background"			        : "",
        "notificationCenterHeader.foreground"			        : "",
        "notificationLink.foreground"			                : "",
        "notifications.background"			                    : "",
        "notifications.border"			                        : "",
        "notifications.foreground"			                    : "",
        "notificationsErrorIcon.foreground"			            : "",
        "notificationsInfoIcon.foreground"			            : "",
        "notificationsWarningIcon.foreground"			        : "",
        "notificationToast.border"			                    : "",
        "panel.background"                                          : "#1E1F29",
        "panel.border"                                              : "#00000070",
        "panel.dropBorder"			                            : "",
        "panelInput.border"			                            : "",
        "panelSection.border"			                        : "",
        "panelSection.dropBackground"			                : "",
        "panelSectionHeader.background"			                : "",
        "panelSectionHeader.border"			                    : "",
        "panelSectionHeader.foreground"			                : "",
        "panelTitle.activeForeground"                               : "#ffffff",
        "panelTitle.inactiveForeground"                             : "#9097A2",
        "peekViewEditor.background"                                 : "#1E1F29",
        "peekViewEditor.matchHighlightBackground"                   : "#558EFF40",
        "peekViewEditorGutter.background"                           : "#1E1F29",
        "peekViewResult.background"                                 : "#23272E",
        "peekViewResult.fileForeground"                         : "",
        "peekViewResult.selectionBackground"                        : "#333842",
        "pickerGroup.border"                                        : "#353A42",
        "pickerGroup.foreground"                                    : "#696F79",
        "ports.iconRunningProcessForeground"	                : "",
        "problemsErrorIcon.foreground"			                : "",
        "problemsInfoIcon.foreground"			                : "",
        "problemsWarningIcon.foreground"		                : "",
        "quickInput.background"			                        : "",
        "quickInput.foreground"			                        : "",
        "quickInputList.focusBackground"	                    : "",
        "quickInputTitle.background"		                    : "",
        "sash.hoverBorder"			                            : "",
        "scm.providerBorder"			                        : "",
        "scrollbar.shadow"                                          : "#1E1F29",
        "searchEditor.findMatchBackground"		                : "",
        "searchEditor.findMatchBorder"			                : "",
        "searchEditor.textInputBorder"			                : "",
        "selection.background"                                      : "#3E4450",
        "settings.checkboxBackground"			                : "",
        "settings.checkboxBorder"			                    : "",
        "settings.checkboxForeground"			                : "",
        "settings.dropdownBackground"			                : "",
        "settings.dropdownBorder"			                    : "",
        "settings.dropdownForeground"			                : "",
        "settings.dropdownListBorder"			                : "",
        "settings.focusedRowBackground"			                : "",
        "settings.headerForeground"			                    : "",
        "settings.modifiedItemIndicator"		                : "",
        "settings.numberInputBackground"		                : "",
        "settings.numberInputBorder"			                : "",
        "settings.numberInputForeground"		                : "",
        "settings.textInputBackground"			                : "",
        "settings.textInputBorder"			                    : "",
        "settings.textInputForeground"			                : "",
        "sideBar.background"                                        : "#252830",
        "sideBar.border"                                            : "#00000030",
        "sideBar.dropBackground"			                    : "",
        "sideBar.foreground"                                        : "#797F8A",
        "sideBarSectionHeader.background"                           : "#1C1D25",
        "sideBarSectionHeader.border"			                : "",
        "statusBar.background"                                      : "#252830",
        "statusBar.border"                                          : "#00000030",
        "statusBar.debuggingBackground"                             : "#DD4941",
        "statusBar.debuggingBorder"			                    : "",
        "statusBar.debuggingForeground"                             : "#ffffff",
        "statusBar.foreground"                                      : "#9095A1",
        "statusBar.noFolderBackground"                              : "#23272E",
        "statusBar.noFolderBorder"			                    : "",
        "statusBar.noFolderForeground"                              : "#9095A1",
        "statusBarItem.activeBackground"                            : "#213237",
        "statusBarItem.errorBackground"			                : "",
        "statusBarItem.errorForeground"			                : "",
        "statusBarItem.hoverBackground"                             : "#213237",
        "statusBarItem.prominentBackground"                     : "",
        "statusBarItem.prominentForeground"			            : "",
        "statusBarItem.remoteBackground"		                : "",
        "statusBarItem.remoteForeground"		                : "",
        "symbolIcon.arrayForeground"			                : "",
        "symbolIcon.booleanForeground"			                : "",
        "symbolIcon.classForeground"			                : "",
        "symbolIcon.colorForeground"			                : "",
        "symbolIcon.constantForeground"			                : "",
        "symbolIcon.constructorForeground"		                : "",
        "symbolIcon.enumeratorForeground"		                : "",
        "symbolIcon.enumeratorMemberForeground"	                : "",
        "symbolIcon.eventForeground"			                : "",
        "symbolIcon.fieldForeground"			                : "",
        "symbolIcon.fileForeground"			                    : "",
        "symbolIcon.folderForeground"			                : "",
        "symbolIcon.functionForeground"			                : "",
        "symbolIcon.interfaceForeground"		                : "",
        "symbolIcon.keyForeground"			                    : "",
        "symbolIcon.keywordForeground"			                : "",
        "symbolIcon.methodForeground"			                : "",
        "symbolIcon.moduleForeground"			                : "",
        "symbolIcon.namespaceForeground"		                : "",
        "symbolIcon.nullForeground"			                    : "",
        "symbolIcon.numberForeground"			                : "",
        "symbolIcon.objectForeground"			                : "",
        "symbolIcon.operatorForeground"			                : "",
        "symbolIcon.packageForeground"			                : "",
        "symbolIcon.propertyForeground"			                : "",
        "symbolIcon.referenceForeground"		                : "",
        "symbolIcon.snippetForeground"			                : "",
        "symbolIcon.stringForeground"			                : "",
        "symbolIcon.structForeground"			                : "",
        "symbolIcon.textForeground"			                    : "",
        "symbolIcon.typeParameterForeground"	                : "",
        "symbolIcon.unitForeground"			                    : "",
        "symbolIcon.variableForeground"			                : "",
        "tab.activeBorderTop"			                        : "",
        "tab.activeModifiedBorder"			                    : "",
        "tab.border"                                                : "#1C1D25",
        "tab.hoverBackground"			                        : "",
        "tab.hoverBorder"			                            : "",
        "tab.hoverForeground"			                        : "",
        "tab.inactiveBackground"                                    : "#282C34",
        "tab.inactiveForeground"                                    : "#ffffff40",
        "tab.inactiveModifiedBorder"			                : "",
        "tab.lastPinnedBorder"			                        : "",
        "tab.unfocusedActiveBackground"			                : "",
        "tab.unfocusedActiveBorder"                                 : "#282C34",
        "tab.unfocusedActiveBorderTop"			                : "",
        "tab.unfocusedActiveForeground"                             : "#ffffff80",
        "tab.unfocusedActiveModifiedBorder"		                : "",
        "tab.unfocusedHoverBackground"			                : "",
        "tab.unfocusedHoverBorder"			                    : "",
        "tab.unfocusedHoverForeground"			                : "",
        "tab.unfocusedInactiveBackground"		                : "",
        "tab.unfocusedInactiveForeground"                           : "#ffffff40",
        "tab.unfocusedInactiveModifiedBorder"			        : "",
        "terminal.ansiBlack"                                        : "#2F3D50",
        "terminal.ansiBlue"                                         : "#4F93D8",
        "terminal.ansiBrightBlack"                                  : "#2D3B4C",
        "terminal.ansiBrightBlue"                                   : "#417EB9",
        "terminal.ansiBrightCyan"                                   : "#45BD9A",
        "terminal.ansiBrightGreen"                                  : "#3BA155",
        "terminal.ansiBrightMagenta"                                : "#954EB4",
        "terminal.ansiBrightRed"                                    : "#DD4941",
        "terminal.ansiBrightWhite"                                  : "#ECF0F1",
        "terminal.ansiBrightYellow"                                 : "#EAC72E",
        "terminal.ansiCyan"                                         : "#3AA184",
        "terminal.ansiGreen"                                        : "#39CA74",
        "terminal.ansiMagenta"                                      : "#8C3BAE",
        "terminal.ansiRed"                                          : "#B73730",
        "terminal.ansiWhite"                                        : "#BEC3C7",
        "terminal.ansiYellow"                                       : "#EA9E2C",
        "terminal.background"                                       : "#1E1F29",
        "terminal.border"			                            : "",
        "terminal.foreground"                                       : "#ffffff",
        "terminal.selectionBackground"	                        : "",
        "terminalCursor.background"		                        : "",
        "terminalCursor.foreground"		                        : "",
        "testing.iconErrored"			                        : "",
        "testing.iconFailed"			                        : "",
        "testing.iconPassed"			                        : "",
        "testing.iconQueued"			                        : "",
        "testing.iconSkipped"			                        : "",
        "testing.iconUnset"			                            : "",
        "testing.message.error.decorationForeground"			: "",
        "testing.message.error.lineBackground"			        : "",
        "testing.message.hint.decorationForeground"			    : "",
        "testing.message.hint.lineBackground"			        : "",
        "testing.message.info.decorationForeground"			    : "",
        "testing.message.info.lineBackground"			        : "",
        "testing.message.warning.decorationForeground"			: "",
        "testing.message.warning.lineBackground"			    : "",
        "testing.peekBorder"			                        : "",
        "testing.runAction"			                            : "",
        "textBlockQuote.background"			                    : "",
        "textBlockQuote.border"			                        : "",
        "textCodeBlock.background"			                    : "",
        "textLink.activeForeground"			                    : "",
        "textLink.foreground"			                        : "",
        "textPreformat.foreground"			                    : "",
        "textSeparator.foreground"			                    : "",
        "titleBar.activeBackground"                                 : "#23272E",
        "titleBar.activeForeground"                                 : "#ffffff",
        "titleBar.border"                                           : "#00000020",
        "titleBar.inactiveBackground"                               : "#23272E",
        "titleBar.inactiveForeground"                               : "#ffffff50",
        "toolbar.activeBackground"                              : "",
        "toolbar.hoverBackground"                               : "",
        "toolbar.hoverOutline"                                  : "",
        "tree.indentGuidesStroke"                               : "",
        "tree.tableColumnsBorder"                               : "",
        "walkThrough.embeddedEditorBackground"                      : "#2C323C7F",
        "welcomePage.background"                                : "",
        "welcomePage.buttonBackground"                              : "#1C1D25",
        "welcomePage.buttonHoverBackground"                         : "#7049B820",
        "welcomePage.progress.background"                       : "",
        "welcomePage.progress.foreground"                       : "",
        "welcomePage.tileBackground"                            : "",
        "welcomePage.tileHoverBackground"                       : "",
        "widget.shadow"                                             : "#1E1F29",
        "window.activeBorder"                                   : "",
        "window.inactiveBorder"                                 : ""
    }
}
