{
    "$schema": "vscode://schemas/color-theme",
    "name": "Fresh Material",
    "include": "./base.json",
    "colors": {
        "activityBar.background"                  : "#E72E6B",
        "activityBar.border"                      : "#000000cc",
        "activityBar.foreground"                  : "#ffffff",
        "activityBarBadge.background"             : "#52FEC2",
        "activityBarBadge.foreground"             : "#00212B80",
        "badge.background"                        : "#406281",
        "badge.foreground"                        : "#ffffff",
        "breadcrumb.foreground"                   : "#ffffff",
        "breadcrumb.focusForeground"              : "#E72E6B",
        "breadcrumb.activeSelectionForeground"    : "#E72E6B",
        "button.background"                       : "#E93D76",
        "button.foreground"                       : "#ffffff",
        "button.hoverBackground"                  : "#E72E6B",
        "debugExceptionWidget.border"             : "#E72E6B",
        "debugToolBar.background"                 : "#E72E6B",
        "editor.inactiveSelectionBackground"      : "#E93D7650",
        "editor.wordHighlightBackground"          : "#E93D7650",
        "editor.wordHighlightStrongBackground"    : "#E72E6B",
        "editorCursor.foreground"                 : "#52FEC2",
        "editorGroup.dropBackground"              : "#E93D7620",
        "editorHoverWidget.border"                : "#E93D76",
        "editorSuggestWidget.foreground"          : "#ffffff",
        "editorSuggestWidget.highlightForeground" : "#ffffff",
        "editorSuggestWidget.selectedBackground"  : "#E93D76",
        "extensionButton.prominentBackground"     : "#E72E6B",
        "extensionButton.prominentForeground"     : "#ffffff",
        "extensionButton.prominentHoverBackground": "#52FEC2",
        "input.border"                            : "#2B2E37",
        "inputOption.activeBorder"                : "#52FEC2",
        "list.activeSelectionBackground"          : "#E93D76",
        "list.activeSelectionForeground"          : "#ffffff",
        "list.dropBackground"                     : "#E93D76",
        "list.focusBackground"                    : "#E93D76",
        "panelTitle.activeBorder"                 : "#E72E6B",
        "peekView.border"                         : "#E72E6B",
        "peekViewResult.lineForeground"           : "#ffffff90",
        "peekViewResult.matchHighlightBackground" : "#E72E6B",
        "peekViewResult.selectionForeground"      : "#ffffff90",
        "peekViewTitle.background"                : "#E72E6B",
        "peekViewTitleDescription.foreground"     : "#ffffff70",
        "peekViewTitleLabel.foreground"           : "#ffffff",
        "progressBar.background"                  : "#65794C",
        "scrollbarSlider.activeBackground"        : "#E72E6B80",
        "scrollbarSlider.background"              : "#E72E6B30",
        "scrollbarSlider.hoverBackground"         : "#E72E6B60",
        "sideBarSectionHeader.foreground"         : "#ffffff",
        "sideBarTitle.foreground"                 : "#E93D76",
        "statusBarItem.remoteForeground"          : "#282C34",
        "statusBarItem.prominentHoverBackground"  : "#E93D767F",
        "tab.activeBackground"                    : "#E93D76",
        "tab.activeBorder"                        : "#52FEC2",
        "tab.activeForeground"                    : "#ffffff"
    }
}
